MANIFEST.in
README.txt
setup.cfg
setup.py
semicinternet/__init__.py
semicinternet.theme.cambrils.egg-info/PKG-INFO
semicinternet.theme.cambrils.egg-info/SOURCES.txt
semicinternet.theme.cambrils.egg-info/dependency_links.txt
semicinternet.theme.cambrils.egg-info/entry_points.txt
semicinternet.theme.cambrils.egg-info/namespace_packages.txt
semicinternet.theme.cambrils.egg-info/not-zip-safe
semicinternet.theme.cambrils.egg-info/paster_plugins.txt
semicinternet.theme.cambrils.egg-info/requires.txt
semicinternet.theme.cambrils.egg-info/top_level.txt
semicinternet/theme/__init__.py
semicinternet/theme/cambrils/__init__.py
semicinternet/theme/cambrils/configure.zcml
semicinternet/theme/cambrils/profiles.zcml
semicinternet/theme/cambrils/setuphandlers.py
semicinternet/theme/cambrils/skins.zcml
semicinternet/theme/cambrils/tests.py
semicinternet/theme/cambrils/version.txt
semicinternet/theme/cambrils/Extensions/Install.py
semicinternet/theme/cambrils/browser/__init__.py
semicinternet/theme/cambrils/browser/configure.zcml
semicinternet/theme/cambrils/browser/controlpanel.py
semicinternet/theme/cambrils/browser/gallery.py
semicinternet/theme/cambrils/browser/homepage.py
semicinternet/theme/cambrils/browser/interfaces.py
semicinternet/theme/cambrils/browser/viewlets.py
semicinternet/theme/cambrils/browser/images/README.txt
semicinternet/theme/cambrils/browser/stylesheets/README.txt
semicinternet/theme/cambrils/browser/templates/colophon.pt
semicinternet/theme/cambrils/browser/templates/dropdown_menu.pt
semicinternet/theme/cambrils/browser/templates/footer.pt
semicinternet/theme/cambrils/browser/templates/gallery.pt
semicinternet/theme/cambrils/browser/templates/global_sections.pt
semicinternet/theme/cambrils/browser/templates/searchbox.pt
semicinternet/theme/cambrils/browser/templates/social_pages.pt
semicinternet/theme/cambrils/locales/README.txt
semicinternet/theme/cambrils/locales/compile_i18n.sh
semicinternet/theme/cambrils/locales/rebuild_i18n.sh
semicinternet/theme/cambrils/locales/semicinternet.theme.cambrils.pot
semicinternet/theme/cambrils/locales/ca/LC_MESSAGES/semicinternet.theme.cambrils.mo
semicinternet/theme/cambrils/locales/ca/LC_MESSAGES/semicinternet.theme.cambrils.po
semicinternet/theme/cambrils/locales/en/LC_MESSAGES/semicinternet.theme.cambrils.mo
semicinternet/theme/cambrils/locales/en/LC_MESSAGES/semicinternet.theme.cambrils.po
semicinternet/theme/cambrils/locales/es/LC_MESSAGES/semicinternet.theme.cambrils.mo
