Metadata-Version: 1.0
Name: semicinternet.theme.cambrils
Version: 1.1.20111207
Summary: A free Plone theme from SEMIC Internet for Plone 4
Home-page: https://github.com/mpampols/semicinternet.theme.cambrils
Author: Marc Pampols
Author-email: mpampols@semicinternet.com
License: GPL
Keywords: semic internet plone theme cambrils
Platform: UNKNOWN
Classifier: Framework :: Plone
Classifier: Programming Language :: Python
